bbt/__init__.py
bbt/tuner.py
bbt/utils.py
bbt_tuner-0.1.0.dist-info/licenses/LICENSE
bbt_tuner-0.1.0.dist-info/METADATA
bbt_tuner-0.1.0.dist-info/WHEEL
bbt_tuner-0.1.0.dist-info/top_level.txt
bbt_tuner-0.1.0.dist-info/RECORD
