Metadata-Version: 2.4
Name: bbt-tuner
Version: 0.1.0
Summary: Adaptive Top-2 Bounding-Box Hyperparameter Tuner
Home-page: https://github.com/abdulvahapmutlu/bounding-box-tuner-bbt
Author: Abdulvahap Mutlu
Author-email: abdulvahapmutlu1@gmail.com
Classifier: Development Status :: 3 - Alpha
Classifier: Intended Audience :: Developers
Classifier: Topic :: Scientific/Engineering :: Artificial Intelligence
Classifier: License :: OSI Approved :: MIT License
Classifier: Programming Language :: Python :: 3
Classifier: Operating System :: OS Independent
Requires-Python: >=3.7
License-File: LICENSE
Requires-Dist: numpy>=1.21
Requires-Dist: scipy>=1.7
Dynamic: author
Dynamic: author-email
Dynamic: classifier
Dynamic: description
Dynamic: description-content-type
Dynamic: home-page
Dynamic: license-file
Dynamic: requires-dist
Dynamic: requires-python
Dynamic: summary
